one_fmt/__init__.py
one_fmt-1.2.0.dist-info/DESCRIPTION.rst
one_fmt-1.2.0.dist-info/METADATA
one_fmt-1.2.0.dist-info/RECORD
one_fmt-1.2.0.dist-info/WHEEL
one_fmt-1.2.0.dist-info/metadata.json
one_fmt-1.2.0.dist-info/top_level.txt
