Metadata-Version: 2.0
Name: one-fmt
Version: 1.2.0
Summary: A module to generate format string exploit shorter than a given length. Currently only supports python2
Home-page: https://github.com/publicqi/one_fmt/
Author: publicqi
Author-email: qisu@ucsb.edu
License: UNKNOWN
Platform: UNKNOWN
